atro_utils/__init__.py
atro_utils/atro_dict.py
atro_utils-0.3.2.dist-info/LICENSE
atro_utils-0.3.2.dist-info/METADATA
atro_utils-0.3.2.dist-info/WHEEL
atro_utils-0.3.2.dist-info/RECORD
