Metadata-Version: 2.1
Name: atro-utils
Version: 0.3.2
Summary: Package containing generic utilities for variety of python usages.
License: MIT
Author: atropos
Author-email: sv7n@pm.me
Requires-Python: >=3.11,<4.0
Classifier: License :: OSI Approved :: MIT License
Classifier: Programming Language :: Python :: 3
Classifier: Programming Language :: Python :: 3.11
Classifier: Programming Language :: Python :: 3.12
Requires-Dist: types-pyyaml (>=6.0.12.20240311,<7.0.0.0)
